Workbook

Sheet Сводный отчет - 2026-05-20T1705
A1: Учредитель | B1: ID ИАС | C1: Наименование организации | D1: ОГРН | E1: Тип организации | F1: Федеральный округ | G1: Регион | H1: Город | I1: Адрес | J1: График работы прямого номера телефона, | K1: Прямой номер телефона приемной комиссии для переадресации звонков, полученных от поступающих на номер Единого контактного центра, | L1: Адрес электронной почты приемной комиссии для принятия тикетов от Единого контактного центра , | M1: часовой пояс
A2: Федеральная служба по надзору в сфере защиты прав потребителей и благополучия человека (Роспотребнадзор) | B2: 7594 | C2: "Ростовский-на-Дону ордена Трудового Красного Знамени научно-исследовательский противочумный институт" Федеральной службы по надзору в сфере защиты прав потребителей и благополучия человека | D2: 1026103278959 | E2: Научные учреждения | F2: Южный ФО | G2: Ростовская область | H2: Ростов-на-Дону | I2: 344002, Ростов-на-Дону, Максима Горького, 117 | J2: Понедельник-пятница: 9:00-16:00, перерыв 12:00-13:00, суббота и воскресенье: выходной | K2: 8(863)285-40-65, доб.1517 | L2: plague@aaanet.ru | M2: =VLOOKUP(G2,справочник!$B$1:$C$94,2,0) -> МСК
A3: Министерство Российской Федерации по делам гражданской обороны, чрезвычайным ситуациям и ликвидации последствий стихийных бедствий (МЧС России) | B3: 580 | C3: Сибирская пожарно-спасательная академия Государственной противопожарной службы Министерства Российской Федерации по делам гражданской обороны, чрезвычайным ситуациям и ликвидации последствий стихийных бедствий | D3: 1157847144542 | E3: Высшее образование | F3: Сибирский ФО | G3: Красноярский край | H3: г Железногорск (Красноярский край | I3: 662972, г Железногорск (Красноярский край, Северная, 1 | J3: понедельник- пятница: 8:30-16:30 суббота и воскресенье: выходной | K3: 83919735425 | L3: sib_umo@mail.ru | M3: =VLOOKUP(G3,справочник!$B$1:$C$94,2,0) -> МСК+4
A4: Негосударственная или частная организация | B4: 7778 | C4: "КОНТУР УНИВЕРСИТЕТ" | D4: 1256600034349 | E4: Высшее образование | F4: Уральский ФО | G4: Свердловская область | H4: Екатеринбург | I4: 620014, Екатеринбург, Проспект Ленина, 20а | J4: понедельник-пятница: 09:00 - 17:00 суббота и воскресенье: выходной | K4: +7 (343) 211-32-29 | L4: priem@konturuniversity.ru | M4: =VLOOKUP(G4,справочник!$B$1:$C$94,2,0) -> МСК+2
A5: Федеральное агентство по недропользованию (Роснедра) | B5: 7616 | C5: «ВСЕРОССИЙСКИЙ ГОСУДАРСТВЕННЫЙ ГЕОЛОГИЧЕСКИЙ НЕФТЯНОЙ ИНСТИТУТ» | D5: 1167746108672 | E5: Научные учреждения | F5: Центральный ФО | G5: г.Москва | H5: г.Москва | I5: 105118, г.Москва, Шоссе Энтузиастов, 36 | J5: Понедельник, среда, четверг с 10.00 до 17.00, суббота и воскресенье: выходной | K5: +7 (499) 781-68-63 доб. 3402 | L5: aspirantura@vnigni.ru | M5: =VLOOKUP(G5,справочник!$B$1:$C$94,2,0) -> МСК
A6: Курчатовский институт | B6: 7591 | C6: «Институт физики высоких энергий имени А.А. Логунова Национального исследовательского центра «Курчатовский институт» | D6: 1125043001357 | E6: Научные учреждения | F6: Центральный ФО | G6: Московская область | H6: Протвино | I6: 142281, Протвино, площадь Науки, 1 | J6: Понедельник-пятница: 9.00-16.30. Суббота и воскресенье: выходные дни. | K6: 8 (916) 730-92-98 | L6: aspirantura_ihep@ihep.ru | M6: =VLOOKUP(G6,справочник!$B$1:$C$94,2,0) -> МСК
A7: Негосударственная или частная организация | B7: 7617 | C7: «Научно-исследовательский «Центр развития энергетического права и современной правовой науки имени В.А. Мусина" | D7: 1207700260360 | E7: Научные учреждения | F7: Центральный ФО | G7: г.Москва | H7: Москва | I7: 123112, Москва, Пресненская набережная, 12 | J7: понедельник-пятница: 9:00-19:00, суббота и воскресенье: выходной | K7: +7 (495) 150-75-69 | L7: musinlc@musinlc.ru | M7: =VLOOKUP(G7,справочник!$B$1:$C$94,2,0) -> МСК
A8: Федеральное агенство по техническому регулированию и метрологии (РОССТАНДАРТ) | B8: 7614 | C8: «Научно-исследовательский центр прикладной метрологии - Ростест» | D8: 1027700066415 | E8: Научные учреждения | F8: Центральный ФО | G8: г.Москва | H8: Москва | I8: 117418, Москва, Нахимовский проспект, 31 | J8: понедельник - четверг: 9:00-17:00, пятница: 9:00-16:00, суббота и воскресенье: выходной | K8: 8 495 437 40 61 | L8: ElenaVR@rostest.ru | M8: =VLOOKUP(G8,справочник!$B$1:$C$94,2,0) -> МСК
A9: Правительство Российской Федерации | B9: 7579 | C9: «Научно-производственное предприятие «Исток» имени А.И. Шокина» | D9: 1135050007400 | E9: Акционерное общество | F9: Центральный ФО | G9: Московская область | H9: Фрязино | I9: 141190, Фрязино, Вокзальная, 2а | J9: Понедельник-пятница: 9:00-16:00 суббота и воскресенье: выходной | K9: 8(495)465-86-80 (доб. 20-45) | L9: aspirantura@istokmw.ru | M9: =VLOOKUP(G9,справочник!$B$1:$C$94,2,0) -> МСК
A10: Правительство Российской Федерации | B10: 4009 | C10: «Петербургский институт ядерной физики им. Б.П. Константинова Национального исследовательского центра «Курчатовский институт» | D10: 1034701242443 | E10: Научные учреждения | F10: Северо-Западный ФО | G10: Ленинградская область | H10: Гатчина | I10: 188300, Гатчина, мкр Орлова роща, 1 | J10: НИЦ "Курчатовский институт" - ПИЯФ: понедельник-пятница, 9:00-12:00, 14:00-17:00; суббота, воскресенье: выходной; филиал НИЦ "Курчатовский институт" - ПИЯФ - ИВС: понедельник-пятница, 10:00-15:00; суббота, воскресенье: выходной; филиал НИЦ "Курчатовский институт" - ПИЯФ - ИХС: понедельник-пятница, 10:00-15:00; суббота, воскресенье: выходной. | K10: НИЦ "Курчатовский институт" - ПИЯФ: 8(81371)46125; филиал НИЦ "Курчатовский институт" - ПИЯФ - ИВС: 8(812)3233345; филиал НИЦ "Курчатовский институт" - ПИЯФ - ИХС: 8(812)3288594. | L10: НИЦ "Курчатовский институт" - ПИЯФ: aspirantura@pnpi.nrcki.ru; филиал НИЦ "Курчатовский институт" - ПИЯФ - ИВС: krasnopeeva_el@pnpi.nrcki.ru; филиал НИЦ "Курчатовский институт" - ПИЯФ - ИХС: sinelshchikova_oy@pnpi.nrcki.ru. | M10: =VLOOKUP(G10,справочник!$B$1:$C$94,2,0) -> МСК
A11: Федеральное агентство водных ресурсов (Росводресурсы) | B11: 7546 | C11: «Российский научно-исследовательский институт комплексного использования и охраны водных ресурсов» | D11: 1156658087739 | E11: Государственные учреждения | F11: Южный ФО | G11: Ростовская область | H11: Ростов-на-Дону | I11: 344037, Ростов-на-Дону, Ченцова, здание 10а | J11: понедельник-пятница: 10:00-16:00 суббота и воскресенье: выходной | K11: +7 (863) 285-30-24 | L11: aspirant-rwec@mail.ru | M11: =VLOOKUP(G11,справочник!$B$1:$C$94,2,0) -> МСК
A12: Негосударственная или частная организация | B12: 7754 | C12: «Тихоокеанский институт предпринимательства, туризма и права» | D12: 1224100003115 | E12: Высшее образование | F12: Дальневосточный ФО | G12: Камчатский край | H12: Петропавловск-Камчатский | I12: 683003, Петропавловск-Камчатский, Ключевская, 11 | J12: понедельник-пятница: 9:00-18:00, суббота 9:00-15:00, воскресенье: выходной | K12: 84152-42-80-01 | L12: info@tiptp.ru | M12: =VLOOKUP(G12,справочник!$B$1:$C$94,2,0) -> МСК+9
A13: Негосударственная или частная организация | B13: 7323 | C13: «Уральский медицинский институт» | D13: 1207400041870 | E13: Высшее образование | F13: Уральский ФО | G13: Челябинская область | H13: Челябинск | I13: 454092, Челябинск, Курчатова, 9 | J13: понедельник-пятница 8:00-17:00, суббота и воскресенье: выходной | K13: +79011479700 | L13: info@umedvuz.ru | M13: =VLOOKUP(G13,справочник!$B$1:$C$94,2,0) -> МСК+2
... A132: Министерство науки и высшего образования Российской Федерации (Минобрнауки России) | B132: 2072 | C132: Всероссийский научно-исследовательский ветеринарный институт патологии, фармакологии и терапии | D132: 1023601576360 | E132: Научные учреждения | F132: Центральный ФО | G132: Воронежская область | H132: Воронеж | I132: 394087, Воронеж, Ломоносова, 114-Б | J132: понедельник-четверг:10:00-15:00, перерыв 12:00-13:00; пятница: 11:00-12:00; суббота и воскресенье: выходной | K132: 8(473)253-92-81 | L132: t.e.lobodina@mail.ru | M132: =VLOOKUP(G132,справочник!$B$1:$C$94,2,0) -> МСК
A133: Федеральное агентство по недропользованию (Роснедра) | B133: 7400 | C133: Всероссийский научно-исследовательский геологический нефтяной институт | D133: 1167746108672 | E133: Научные учреждения | F133: Центральный ФО | G133: г.Москва | J133: понедельник:10.00 -17.00 среда:10.00 - 17.00 четверг:10.00 - 17.00 суббота и воскресенье: выходной | K133: +7 (499) 781-68-63 | L133: aspirantura@vnigni.ru | M133: =VLOOKUP(G133,справочник!$B$1:$C$94,2,0) -> МСК
A134: Министерство сельского хозяйства Российской Федерации (Минсельхоз России) | B134: 2559 | C134: Всероссийский научно-исследовательский и технологический институт биологической промышленности | D134: 1035010214436 | E134: Научные учреждения | F134: Центральный ФО | G134: Московская область | H134: поселок Биокомбината | I134: 141142, поселок Биокомбината, х, 17 | J134: понедельник-четверг: 8:00-17:00 пятница:8:00-16:00 суббота и воскресенье: выходной | K134: +7 (496) 567-32-63 | L134: centrkomp_vnitibp@mail.ru | M134: =VLOOKUP(G134,справочник!$B$1:$C$94,2,0) -> МСК
A135: Негосударственная или частная организация | B135: 3157 | C135: Всероссийский научно-исследовательский институт авиационных материалов Национального исследовательского центра «Курчатовский институт» | D135: 1027739045399 | E135: Унитарные предприятия | F135: Центральный ФО | G135: г.Москва | H135: Москва | I135: 105005, Москва, Радио, 17 | J135: понедельник-четверг: 9:00-17:30 пятница: 9:00-16:30 обед: 13:00-14:00 суббота и воскресенье: выходной | K135: 8-499-263-86-62 | L135: priem@viam.ru | M135: =VLOOKUP(G135,справочник!$B$1:$C$94,2,0) -> МСК
A136: Министерство науки и высшего образования Российской Федерации (Минобрнауки России) | B136: 1880 | C136: Всероссийский научно-исследовательский институт агрохимии имени Д.Н. Прянишникова | D136: 1037713026560 | E136: Научные учреждения | F136: Центральный ФО | G136: г.Москва | H136: Москва | I136: 127434, Москва, улица Прянишникова, 31 а | J136: понедельник-четверг: 9:30-17:30 пятница: 9:30-16:00 | K136: +7 (499) 977-09-44 | L136: aspirantura@vniia-pr.ru, kpk@vniia-pr.ru | M136: =VLOOKUP(G136,справочник!$B$1:$C$94,2,0) -> МСК
A137: Министерство науки и высшего образования Российской Федерации (Минобрнауки России) | B137: 2943 | C137: Всероссийский научно-исследовательский институт защиты растений | D137: 1027809005124 | E137: Научные учреждения | F137: Северо-Западный ФО | G137: г.Санкт-Петербург | H137: Пушкин | I137: 196608, Пушкин, шоссе Подбельского, 3 | J137: понедельник-четверг: 10:00-15:00 пятница, суббота и воскресенье:выходной | K137: 8(812)4704384 | L137: graduate@vizr.spb.ru | M137: =VLOOKUP(G137,справочник!$B$1:$C$94,2,0) -> МСК
A138: Министерство науки и высшего образования Российской Федерации (Минобрнауки России) | B138: 2638 | C138: Всероссийский научно-исследовательский институт коневодства имени академика В.В. Калашникова | D138: 1036216005231 | E138: Научные учреждения | F138: Центральный ФО | G138: Рязанская область | H138: Дивово | I138: 391105, Дивово, Ученых, нет | J138: понедельник-четверг: 9:00-16:30, пятница: 9:00-14:00 | K138: (4912)24-02-65, доп. 115 | L138: vniik08@mail.ru | M138: =VLOOKUP(G138,справочник!$B$1:$C$94,2,0) -> МСК
A139: Министерство науки и высшего образования Российской Федерации (Минобрнауки России) | B139: 1864 | C139: Всероссийский научно-исследовательский институт лекарственных и ароматических растений | D139: 1027700388066 | E139: Научные учреждения | F139: Центральный ФО | G139: г.Москва | H139: Москва | I139: 117216, Москва, Грина, 7 | J139: понедельник-четверг: 10:00-17:00 пятница: 10:00-16:00 суббота и воскресенье: выходной | K139: 8(495)712-16-63 | L139: lanatomilova@yandex.ru | M139: =VLOOKUP(G139,справочник!$B$1:$C$94,2,0) -> МСК
A140: Федеральное агентство лесного хозяйства (Рослесхоз) | B140: 3432 | C140: Всероссийский научно-исследовательский институт лесоводства и механизации лесного хозяйства | D140: 1025004911315 | E140: Научные учреждения | F140: Центральный ФО | G140: Московская область | H140: Пушкино | I140: 141202, Пушкино, Институтская, 15 | J140: понедельник-четверг: 10:00-17:00 пятница: 10:00-16:00 суббота и воскресенье: выходной | K140: 8-495-993-30-54 | L140: nmo@vniilm.ru | M140: =VLOOKUP(G140,справочник!$B$1:$C$94,2,0) -> МСК
A141: Федеральное агенство по техническому регулированию и метрологии (РОССТАНДАРТ) | B141: 3451 | C141: Всероссийский научно-исследовательский институт метрологии им. Д.И. Менделеева | D141: 1027810219007 | E141: Научные учреждения | F141: Северо-Западный ФО | G141: г.Санкт-Петербург | H141: Санкт-петербург | I141: 190005, Санкт-петербург, Московский проспект, 19 | J141: понедельник-четверг: 9:00-17:00 пятница: 9:00-14.15 суббота и воскресенье: выходной | K141: 8(812)323-93-79 | L141: a.a.tinkova@vniim.ru | M141: =VLOOKUP(G141,справочник!$B$1:$C$94,2,0) -> МСК
A142: Министерство науки и высшего образования Российской Федерации (Минобрнауки России) | B142: 1805 | C142: Всероссийский научно-исследовательский институт молочной промышленности | D142: 1037739374672 | E142: Научные учреждения | F142: Центральный ФО | G142: г.Москва | H142: Москва | I142: 115093, Москва, Люсиновская, 35 | J142: понедельник-вторник: 10:00-16:00 среда-воскресенье: выходной | K142: - | L142: aspirantura@vnimi.org | M142: =VLOOKUP(G142,справочник!$B$1:$C$94,2,0) -> МСК
A143: Федеральное агенство по техническому регулированию и метрологии (РОССТАНДАРТ) | B143: 3429 | C143: Всероссийский научно-исследовательский институт оптико-физических измерений | D143: 1237700065470 | E143: Государственные учреждения | F143: Центральный ФО | G143: г.Москва | H143: Москва | I143: 119361, Москва, Озерная, 46 | J143: понедельник-четверг: 10:00-17:00, пятница: 10:00-16:00, суббота и воскресенье: выходной | K143: +74957812447 | L143: science@vniiofi.ru | M143: =VLOOKUP(G143,справочник!$B$1:$C$94,2,0) -> МСК
A144: Министерство науки и высшего образования Российской Федерации (Минобрнауки России) | B144: 2296 | C144: Всероссийский научно-исследовательский институт охотничьего хозяйства и звероводства имени профессора Б.М. Житкова | D144: 1024301308680 | E144: Научные учреждения | F144: Приволжский ФО | G144: Кировская область | H144: Киров | I144: 610020, Киров, Преображенская, 79 | J144: понедельник-четверг: 9:00-17:30, пятница: 9:00-16:00, суббота и воскресенье: выходной | K144: 8(8332) 64-66-61 | L144: aspirantura@vniioz-kirov.ru | M144: =VLOOKUP(G144,справочник!$B$1:$C$94,2,0) -> МСК
A145: Федеральное агентство по рыболовству (Росрыболовство) | B145: 3608 | C145: Всероссийский научно-исследовательский институт рыбного хозяйства и океанографии | D145: 1157746053431 | E145: Научные учреждения | F145: Центральный ФО | G145: г.Москва | H145: Москва | I145: 105187, Москва, Окружной проезд, 19 | J145: понедельник-четверг: 10:00-17:00 пятница: 10:00-16:00 суббота и воскресенье: выходной | K145: 84993690306 | L145: aspirant@vniro.ru | M145: =VLOOKUP(G145,справочник!$B$1:$C$94,2,0) -> МСК
... A346: Министерство науки и высшего образования Российской Федерации (Минобрнауки России) | B346: 2698 | C346: Институт органической химии им. Н.Д. Зелинского Российской академии наук | D346: 1027700304323 | E346: Научные учреждения | F346: Центральный ФО | G346: г.Москва | H346: МОСКВА | I346: 119991, МОСКВА, ПРОСПЕКТ ЛЕНИНСКИЙ, д 47 | J346: понедельник-четверг: 11:00-18:30 пятница: 11:00-16:30 суббота и воскресенье: выходной | K346: 8-499-137-71-91 | L346: vesela@ioc.ac.ru | M346: =VLOOKUP(G346,справочник!$B$1:$C$94,2,0) -> МСК
A347: Субъект Российской Федерации | B347: 7349 | C347: Институт повышения квалификации руководящих работников и специалистов | D347: 1035002452132 | E347: Образовательные учреждение дополнительного профессионального образования | F347: Центральный ФО | G347: Московская область | J347: Понедельник-пятница с 09:00 до 17:00 Суббота, воскресень выходной день | K347: 8-925-629-1105 | L347: i.voropaev@ipkmeteo.ru | M347: =VLOOKUP(G347,справочник!$B$1:$C$94,2,0) -> МСК
A348: Министерство науки и высшего образования Российской Федерации (Минобрнауки России) | B348: 2202 | C348: Институт прикладной астрономии Российской академии наук | D348: 1037828005852 | E348: Научные учреждения | F348: Северо-Западный ФО | G348: г.Санкт-Петербург | H348: Санкт-Петербург | I348: 191187, Санкт-Петербург, Кутузова набережная, 10 | J348: понедельник-пятница: 10:00-17:00, суббота и воскресенье: выходной | K348: 8 (812) 275 10 15 | L348: zmb@iaaras.ru | M348: =VLOOKUP(G348,справочник!$B$1:$C$94,2,0) -> МСК
A349: Министерство науки и высшего образования Российской Федерации (Минобрнауки России) | B349: 1854 | C349: Институт прикладной механики Российской академии наук | D349: 1037700153182 | E349: Научные учреждения | F349: Центральный ФО | G349: г.Москва | H349: Москва | I349: 125040, Москва, Ленинградский проспект, 7 | J349: понедельник-четверг: 12:00-16:00 пятница-воскресенье: выходной | K349: +7(906)726-06-88 | L349: aspirantura@iam.ras.ru | M349: =VLOOKUP(G349,справочник!$B$1:$C$94,2,0) -> МСК
A350: Министерство науки и высшего образования Российской Федерации (Минобрнауки России) | B350: 1964 | C350: Институт проблем безопасного развития атомной энергетики Российской академии наук | D350: 1027700196468 | E350: Научные учреждения | F350: Центральный ФО | G350: г.Москва | H350: Москва | I350: 115191, Москва, Тульская Б., 52 | J350: понедельник- четверг: 9:00-16:00 пятница : 9:00-15:00 суббота и воскресенье: выходной | K350: 8-495-955-23-10 | L350: pbl@ibrae.ac.ru | M350: =VLOOKUP(G350,справочник!$B$1:$C$94,2,0) -> МСК
A351: Министерство науки и высшего образования Российской Федерации (Минобрнауки России) | B351: 4032 | C351: Институт проблем искусственного интеллекта | D351: 1229300155182 | E351: Научные учреждения | F351: Южный ФО | G351: Донецкая Народная Республика | H351: Донецк | I351: 283048, Донецк, Артема, 118Б | J351: понедельник-пятница: 10:00-15:00 суббота и воскресенье: выходной | K351: +7(949) 439-76-82 | L351: aspirantura.ipai@yandex.ru | M351: =VLOOKUP(G351,справочник!$B$1:$C$94,2,0) -> МСК
A352: Министерство науки и высшего образования Российской Федерации (Минобрнауки России) | B352: 1788 | C352: Институт проблем комплексного освоения недр им. академика Н.В. Мельникова Российской академии наук | D352: 1037700121150 | E352: Научные учреждения | F352: Центральный ФО | G352: г.Москва | H352: Москва | I352: 111020, Москва, Крюковский туп., 4 | J352: понедельник-четверг: 12:00-17:00 пятница: 12:00-16:30 суббота и воскресенье: выходной | K352: +7(495) 360-49-04 | L352: aspirantyra_ipkon@mail.ru | M352: =VLOOKUP(G352,справочник!$B$1:$C$94,2,0) -> МСК
A353: Министерство науки и высшего образования Российской Федерации (Минобрнауки России) | B353: 1783 | C353: Институт проблем машиноведения Российской академии наук | D353: 1037800003560 | E353: Научные учреждения | F353: Северо-Западный ФО | G353: г.Санкт-Петербург | H353: Санкт-Петербург | I353: 199178, Санкт-Петербург, Васильевский остров. Большой проспект, 61 | J353: понедельник-четверг: 10:30-17:30 пятница: 10:30-16:30 суббота и воскресенье: выходной | K353: 8(812)321-47-72 | L353: aspirant@ipme.ru | M353: =VLOOKUP(G353,справочник!$B$1:$C$94,2,0) -> МСК
A354: Министерство науки и высшего образования Российской Федерации (Минобрнауки России) | B354: 1791 | C354: Институт проблем механики им. А.Ю. Ишлинского Российской академии наук | D354: 1037739426735 | E354: Научные учреждения | F354: Центральный ФО | G354: г.Москва | H354: Москва | I354: 119526, Москва, проспект Вернадского, 101 | J354: Понедельник - четверг 10:00 - 16:00, пятница 10:00 - 15:00, суббота и воскресенье: выходной. | K354: +7-495- 4343351 | L354: aspirantura@ipmnet.ru | M354: =VLOOKUP(G354,справочник!$B$1:$C$94,2,0) -> МСК
A355: Министерство науки и высшего образования Российской Федерации (Минобрнауки России) | B355: 2749 | C355: Институт проблем морских технологий им. академика М.Д. Агеева Дальневосточного отделения Российской академии наук | D355: 1022501279877 | E355: Научные учреждения | F355: Дальневосточный ФО | G355: Приморский край | H355: Владивосток | I355: 690091, Владивосток, Суханова, 5а | J355: понедельник-пятница: 9:00-15:00 суббота и воскресенье: выходной | K355: +7 (423) 243-24-16 | L355: aspirant@marine.febras.ru | M355: =VLOOKUP(G355,справочник!$B$1:$C$94,2,0) -> МСК+7
A356: Министерство науки и высшего образования Российской Федерации (Минобрнауки России) | B356: 2257 | C356: Институт проблем нефти и газа Российской академии наук | D356: 1037739238195 | E356: Научные учреждения | F356: Центральный ФО | G356: г.Москва | H356: Москва | I356: 119333, Москва, Губкина, 3 | J356: понедельник-вторник-четверг: 11:00-17:00 пятница: 11:00-16:00 суббота и воскресенье: выходной | K356: 84991357311 | L356: aspirant@ipng.ru | M356: =VLOOKUP(G356,справочник!$B$1:$C$94,2,0) -> МСК
A357: Министерство науки и высшего образования Российской Федерации (Минобрнауки России) | B357: 2331 | C357: Институт проблем передачи информации им. А.А. Харкевича Российской академии наук | D357: 1037700064940 | E357: Научные учреждения | F357: Центральный ФО | G357: г.Москва | H357: Москва | I357: 127051, Москва, Большой Каретный переулок, 19 | J357: Пример: понедельник-четверг: 9:00-17:30 пятница суббота и воскресенье: выходной | K357: 8-495-699-54-91 | L357: naumova@iitp.ru | M357: =VLOOKUP(G357,справочник!$B$1:$C$94,2,0) -> МСК
A358: Министерство науки и высшего образования Российской Федерации (Минобрнауки России) | B358: 1778 | C358: Институт проблем развития науки Российской академии наук | D358: 1057747667658 | E358: Научные учреждения | F358: Центральный ФО | G358: г.Москва | H358: Москва | I358: 117218, Москва, Нахимовский пр-т, 32 | J358: - | K358: 8(495)2490274 | L358: posta@issras.ru | M358: =VLOOKUP(G358,справочник!$B$1:$C$94,2,0) -> МСК
A359: Министерство науки и высшего образования Российской Федерации (Минобрнауки России) | B359: 1916 | C359: Институт проблем региональной экономики Российской академии наук | D359: 1037851003574 | E359: Научные учреждения | F359: Северо-Западный ФО | G359: г.Санкт-Петербург | H359: Санкт-Петербург | I359: 190013, Санкт-Петербург, Серпуховская, 38 | J359: Понедельник: 11-15 часов Среда: 11-15часов | K359: (812) 3164865 | L359: info@iresras.ru | M359: =VLOOKUP(G359,справочник!$B$1:$C$94,2,0) -> МСК
... A500: Министерство спорта Российской Федерации (Минспорт России) | B500: 537 | C500: Кубанский государственный университет физической культуры, спорта и туризма | D500: 1022301597647 | E500: Высшее образование | F500: Южный ФО | G500: Краснодарский край | H500: Краснодар | I500: 350015, Краснодар, им.Буденного, 161 | J500: Понедельник-пятница: 9:00-17:00, суббота: 9:00-14:00 | K500: +7(861)259-26-77 | L500: priem@kgufkst.ru | M500: =VLOOKUP(G500,справочник!$B$1:$C$94,2,0) -> МСК
A501: Негосударственная или частная организация | B501: 7322 | C501: КУБАНСКИЙ ИНСТИТУТ ПРОФЕССИОНАЛЬНОГО ОБРАЗОВАНИЯ | D501: 1222300063501 | E501: Высшее образование | F501: Южный ФО | G501: Краснодарский край | J501: понедельник-четверг: 8:00-17:00 пятница: 8:00-16:00 суббота и воскресенье: выходной | K501: 89180680088 | L501: priem@kipo.institute | M501: =VLOOKUP(G501,справочник!$B$1:$C$94,2,0) -> МСК
A502: Негосударственная или частная организация | B502: 2886 | C502: Кубанский медицинский институт | D502: 1022301979534 | E502: Высшее образование | F502: Южный ФО | G502: Краснодарский край | H502: Краснодар | I502: 350064, Краснодар, Красная/им. Ленина, 52-56/44 | J502: 10.00 - 18.00 понедельник - пятница, суббота и воскресенье выходной | K502: 8(861)991-22-88 | L502: info@kubmi.ru | M502: =VLOOKUP(G502,справочник!$B$1:$C$94,2,0) -> МСК
A503: Министерство сельского хозяйства Российской Федерации (Минсельхоз России) | B503: 645 | C503: Кузбасский государственный аграрный университет имени В.Н. Полецкова | D503: 1024240680199 | E503: Высшее образование | F503: Сибирский ФО | G503: Кемеровская область | H503: Кемерово | I503: 650056, Кемерово, ул. Марковцева, 5, ул. Марковцева, 5 | J503: понедельник- пятница: 9:00-17.15; суббота: 9:00-14:00; воскресенье: выходной | K503: 83842734375 | L503: priemksai@mail.ru | M503: =VLOOKUP(G503,справочник!$B$1:$C$94,2,0) -> МСК+4
A504: Министерство науки и высшего образования Российской Федерации (Минобрнауки России) | B504: 83 | C504: Кузбасский государственный технический университет имени Т.Ф. Горбачева | D504: 1024200708069 | E504: Высшее образование | F504: Сибирский ФО | G504: Кемеровская область | H504: Кемерово | I504: 650000, Кемерово, Весенняя, 28 | J504: с 1 сентября по 19 июня: понедельник-четверг: 8:00-17:00 пятница: 8:00-14:30 суббота и воскресенье: выходной; с 20 июня по 31 августа: понедельник-пятница: 9:00-18:00 суббота: 10:00-14:00 воскресенье: выходной | K504: 8 (3842) 68-24-24 | L504: abit@kuzstu.ru | M504: =VLOOKUP(G504,справочник!$B$1:$C$94,2,0) -> МСК+4
A505: Министерство науки и высшего образования Российской Федерации (Минобрнауки России) | B505: 84 | C505: Курганский государственный университет | D505: 1024500512410 | E505: Высшее образование | F505: Уральский ФО | G505: Курганская область | H505: Курган | I505: 640020, Курган, Советская, 63 | J505: Понедельник-пятница: 9:00-17:00; суббота и воскресенье: выходной | K505: 8 (3522) 65-30-30 | L505: pk@kgsu.ru | M505: =VLOOKUP(G505,справочник!$B$1:$C$94,2,0) -> МСК+2
A506: Субъект Российской Федерации | B506: 3172 | C506: Курская академия государственной и муниципальной службы | D506: 1034637002256 | E506: Высшее образование | F506: Центральный ФО | G506: Курская область | H506: Курск | I506: 305044, Курск, Станционная, 9 | J506: Понедельник-четверг: 9:00-17:00 пятница: 9:00-16:00 суббота и воскресенье: 9:00-13:30 | K506: +7(961)191-58-00 | L506: pkkagms2020@mail.ru | M506: =VLOOKUP(G506,справочник!$B$1:$C$94,2,0) -> МСК
A507: Министерство сельского хозяйства Российской Федерации (Минсельхоз России) | B507: 739 | C507: Курский государственный аграрный университет имени И.И. Иванова | D507: 1034637005292 | E507: Высшее образование | F507: Центральный ФО | G507: Курская область | H507: Курск | I507: 305021, Курск, Карла Маркса, 70 | J507: понедельник-пятница: 9:00-17:00 суббота- воскресенье: 10:00-14:00 | K507: +74712394020 | L507: priem.kurskgsha@mail.ru | M507: =VLOOKUP(G507,справочник!$B$1:$C$94,2,0) -> МСК
A508: Министерство здравоохранения Российской Федерации (Минздрав России) | B508: 579 | C508: Курский государственный медицинский университет Министерства здравоохранения Российской Федерации | D508: 1034637005347 | E508: Высшее образование | F508: Центральный ФО | G508: Курская область | H508: г Курск | I508: 305041, г Курск, ул К. Маркса, 3 | J508: понедельник-пятница: 10:00-16:00 суббота: 10:00 -12:00; воскресенье: выходной | K508: +74712745048 - 20 июня - 29 августа; +74712588138 - 30 августа-19 июня | L508: shepelevaom@kursksmu.net | M508: =VLOOKUP(G508,справочник!$B$1:$C$94,2,0) -> МСК
A509: Министерство науки и высшего образования Российской Федерации (Минобрнауки России) | B509: 86 | C509: Курский государственный университет | D509: 1024600954608 | E509: Высшее образование | F509: Центральный ФО | G509: Курская область | H509: Курск | I509: 305000, Курск, Радищева, 33 | J509: понедельник-пятница: 9.00-16.00 суббота: 9.00 - 13.00 воскресенье: выходной | K509: +74712520904 | L509: pk@kursksu.ru | M509: =VLOOKUP(G509,справочник!$B$1:$C$94,2,0) -> МСК
A510: Негосударственная или частная организация | B510: 3374 | C510: Курский институт менеджмента, экономики и бизнеса | D510: 1024600966422 | E510: Высшее образование | F510: Центральный ФО | G510: Курская область | H510: Курск | I510: 305000, Курск, Радищева, 35 | J510: понедельник-пятница: 9-00-18-00 суббота и воскресенье: выходной | K510: +74712705690 | L510: priem@mebik.ru | M510: =VLOOKUP(G510,справочник!$B$1:$C$94,2,0) -> МСК
A511: Министерство науки и высшего образования Российской Федерации (Минобрнауки России) | B511: 2106 | C511: Курский федеральный аграрный научный центр | D511: 1024600618690 | E511: Научные учреждения | F511: Центральный ФО | G511: Курская область | H511: Курск | I511: 305021, Курск, Карла Маркса, 70 | J511: Понедельник-пятница 09:00-16:00, перерыв с 13:00 до 14:00 | K511: +7(4712)53-78-12 | L511: kurskfarc@mail.ru | M511: =VLOOKUP(G511,справочник!$B$1:$C$94,2,0) -> МСК
A512: Субъект Российской Федерации | B512: 3220 | C512: Ленинградский государственный университет имени А.С. Пушкина | D512: 1024701897043 | E512: Высшее образование | F512: Северо-Западный ФО | G512: г.Санкт-Петербург | H512: Пушкин | I512: 196605, Пушкин, Петербургское шоссе, 10 | J512: Понедельник-пятница: 9:00-17:00. Суббота: 9:00-14:00. Воскресенье: выходной | K512: 8 (812) 500-94-89 | L512: priemlgu@lengu.ru | M512: =VLOOKUP(G512,справочник!$B$1:$C$94,2,0) -> МСК
A513: Министерство науки и высшего образования Российской Федерации (Минобрнауки России) | B513: 2140 | C513: Лимнологический институт Сибирского отделения Российской академии наук | D513: 1023801757540 | E513: Научные учреждения | F513: Сибирский ФО | G513: Иркутская область | H513: Иркутск | I513: 664033, Иркутск, Улан-Баторская, 3 | J513: Понедельник-пятница: 9.00-18.00 обед 12.00-13.00 суббота и воскресенье: выходной | K513: 8(3952) 42-30-53 | L513: lomakina@lin.irk.ru | M513: =VLOOKUP(G513,справочник!$B$1:$C$94,2,0) -> МСК+5
... A860: Негосударственная или частная организация | B860: 3378 | C860: Русская христианская гуманитарная академия им. Ф.М. Достоевского | D860: 1227800162028 | E860: Высшее образование | F860: Северо-Западный ФО | G860: г.Санкт-Петербург | H860: Санкт-Петербург | I860: 191011, Санкт-Петербург, набережная реки Фонтанки, 15 | J860: понедельник - пятница: 10.30 - 17.30, суббота и воскресенье -выходной. | K860: +78123341441 | L860: abiturient@rhga.ru | M860: =VLOOKUP(G860,справочник!$B$1:$C$94,2,0) -> МСК
A861: Негосударственная или частная организация | B861: 7548 | C861: Русский университет метатехнологий | D861: 1091200000495 | E861: Высшее образование | F861: Приволжский ФО | G861: Республика Марий Эл | J861: понедельник-пятница: 9:00-18:00 перерыв: 12:00-13:00 суббота и воскресенье: выходной | K861: +7 (8362) 60 00 10, +7 939 720 00 10 | L861: institute@ispring.ru | M861: =VLOOKUP(G861,справочник!$B$1:$C$94,2,0) -> МСК
A862: Министерство науки и высшего образования Российской Федерации (Минобрнауки России) | B862: 168 | C862: Рыбинский государственный авиационный технический университет имени П. А. Соловьева | D862: 1027601126057 | E862: Высшее образование | F862: Центральный ФО | G862: Ярославская область | H862: Рыбинск | I862: 152934, Рыбинск, Пушкина, 53 | J862: С 1 сентября до 19 июня: понедельник-пятница: 9:00-12:45, 14:00-17:45, суббота и воскресенье - выходной. С 20 июня до 29 августа понедельник-пятница: 9:00-12:45, 14:00-17:45, суббота: 9:00-12:45, воскресенье - выходной. | K862: 8(4855)23-97-60 | L862: pk@rsatu.ru | M862: =VLOOKUP(G862,справочник!$B$1:$C$94,2,0) -> МСК
A863: Министерство сельского хозяйства Российской Федерации (Минсельхоз России) | B863: 573 | C863: Рязанский государственный агротехнологический университет имени П.А. Костычева | D863: 1026201074998 | E863: Высшее образование | F863: Центральный ФО | G863: Рязанская область | H863: Рязань | I863: 390044, Рязань, Костычева, 1 | J863: понедельник-суббота : 9:00-18:00 воскресенье: выходной | K863: 8 (4912) 35-10-56 | L863: priem@rgatu.ru | M863: =VLOOKUP(G863,справочник!$B$1:$C$94,2,0) -> МСК
A864: Министерство здравоохранения Российской Федерации (Минздрав России) | B864: 687 | C864: Рязанский государственный медицинский университет имени академика И.П. Павлова Министерства здравоохранения Российской Федерации | D864: 1036212013408 | E864: Высшее образование | F864: Центральный ФО | G864: Рязанская область | H864: Рязань | I864: 390026, Рязань, Высоковольтная, 9 | J864: Понедельник - пятница: с 9.00 до 17.00 Суббота: с 9.00 до 15.00 Воскресенье - выходной | K864: +7(4912) 97-18-48 | L864: priem@rzgmu.ru | M864: =VLOOKUP(G864,справочник!$B$1:$C$94,2,0) -> МСК
A865: Министерство науки и высшего образования Российской Федерации (Минобрнауки России) | B865: 169 | C865: Рязанский государственный радиотехнический университет имени В.Ф. Уткина | D865: 1026201104478 | E865: Высшее образование | F865: Центральный ФО | G865: Рязанская область | H865: Рязань | I865: 390005, Рязань, ул. Гагарина, 59/1 | J865: 09:00-17:00 | K865: 8(4912)72-04-24 | L865: pk@rsreu.ru | M865: =VLOOKUP(G865,справочник!$B$1:$C$94,2,0) -> МСК
A866: Министерство науки и высшего образования Российской Федерации (Минобрнауки России) | B866: 170 | C866: Рязанский государственный университет имени С.А. Есенина | D866: 1026201268301 | E866: Высшее образование | F866: Центральный ФО | G866: Рязанская область | H866: Рязань | I866: 390000, Рязань, Свободы, 46 | J866: понедельник-пятница: 9:00-17:00 суббота: 9:00-14:00 воскресенье: выходной | K866: 8 (4912) 97-15-10 | L866: priem@rsu-rzn.ru | M866: =VLOOKUP(G866,справочник!$B$1:$C$94,2,0) -> МСК
A867: Министерство сельского хозяйства Российской Федерации (Минсельхоз России) | B867: 1268 | C867: Самарский государственный аграрный университет | D867: 1026303273061 | E867: Высшее образование | F867: Приволжский ФО | G867: Самарская область | H867: Усть-Кинельский | I867: 446442, Усть-Кинельский, Учебная, 2 | J867: Понедельник-пятница: 8:00-16:00, суббота 8:00-12:00, воскресенье: выходной | K867: 89397540486 | L867: pk_ssaa@mail.ru | M867: =VLOOKUP(G867,справочник!$B$1:$C$94,2,0) -> МСК+1
A868: Министерство культуры Российской Федерации (Минкультуры России) | B868: 727 | C868: Самарский государственный институт культуры | D868: 1026300966361 | E868: Высшее образование | F868: Приволжский ФО | G868: Самарская область | H868: Самара | I868: 443010, Самара, Фрунзе, 167 | J868: понедельник-пятница: 10:00-16:00 суббота и воскресенье: выходной | K868: +78463332222 | L868: priem@samgik.ru | M868: =VLOOKUP(G868,справочник!$B$1:$C$94,2,0) -> МСК+1
A869: Министерство здравоохранения Российской Федерации (Минздрав России) | B869: 550 | C869: Самарский государственный медицинский университет Министерства здравоохранения Российской Федерации | D869: 1026301426348 | E869: Высшее образование | F869: Приволжский ФО | G869: Самарская область | H869: Самара | I869: 443099, Самара, Чапаевская 89, 89 | J869: Понедельник-четверг: 9:00-18:00, пятница: 9:00-17:00, суббота и воскресенье: выходной | K869: +7 (846) 374-00-11 | L869: priem@samsmu.ru | M869: =VLOOKUP(G869,справочник!$B$1:$C$94,2,0) -> МСК+1
A870: Министерство просвещения Российской Федерации (Минпросвещения России) | B870: 150 | C870: Самарский государственный социально-педагогический университет | D870: 1036300661242 | E870: Высшее образование | F870: Приволжский ФО | G870: Самарская область | H870: Самара | I870: 443099, Самара, ул. М. Горького, 65/67 | J870: 8 (846) 207 88-77 Понедельник - Пятница: 09:00 - 16:00 Суббота: 09:00 - 13:00 Воскресенье: выходной | K870: 8 (846) 207 88-77 | L870: priem@sgspu.ru | M870: =VLOOKUP(G870,справочник!$B$1:$C$94,2,0) -> МСК+1
A871: Министерство науки и высшего образования Российской Федерации (Минобрнауки России) | B871: 186 | C871: Самарский государственный технический университет | D871: 1026301167683 | E871: Высшее образование | F871: Приволжский ФО | G871: Самарская область | H871: Самара | I871: 443100, Самара, Молодогвардейская, 244 | J871: Будни с 9 до 17 часов Суббота с 10 до 14 часов Воскресенье выходной | K871: 8 (800) 302 17 71 | L871: priem@samgtu.ru | M871: =VLOOKUP(G871,справочник!$B$1:$C$94,2,0) -> МСК+1
A872: Министерство науки и высшего образования Российской Федерации (Минобрнауки России) | B872: 188 | C872: Самарский государственный экономический университет | D872: 1026301505120 | E872: Высшее образование | F872: Приволжский ФО | G872: Самарская область | H872: Самара | I872: 443090, Самара, Советской Армии, 141 | J872: понедельник-четверг: 9:00-18:00, пятница-суббота: 9:00-16:00, воскресенье: выходной | K872: 8 (846) 215-31-63 | L872: priem@sseu.ru | M872: =VLOOKUP(G872,справочник!$B$1:$C$94,2,0) -> МСК+1
A873: Министерство науки и высшего образования Российской Федерации (Минобрнауки России) | B873: 185 | C873: Самарский национальный исследовательский университет имени академика С.П. Королева | D873: 1026301168310 | E873: Высшее образование | F873: Приволжский ФО | G873: Самарская область | H873: Самара | I873: 443086, Самара, Московское шоссе, 34 | J873: понедельник-пятница: 10:00-16:00 суббота: 10:00-14:00 воскресенье: выходной, время местное | K873: 8 (800) 550-34-35 | L873: priem@ssau.ru | M873: =VLOOKUP(G873,справочник!$B$1:$C$94,2,0) -> МСК+1
... A933: Негосударственная или частная организация | B933: 1431 | C933: Северо-Кавказский социальный институт | D933: 1162651055346 | E933: Высшее образование | F933: Северо-Кавказский ФО | G933: Ставропольский край | H933: Ставрополь | I933: 355012, Ставрополь, Голенева, 59А | J933: понедельник-пятница: 9:00-17:00: суббота: 9:00-14:00 воскресенье: выходной | K933: +7-962-446-94-54 | L933: abitur-sksi@mail.ru | M933: =VLOOKUP(G933,справочник!$B$1:$C$94,2,0) -> МСК
A934: Негосударственная или частная организация | B934: 7759 | C934: Северо-Кавказский университет дружбы народов | D934: 1210500016880 | E934: Высшее образование | F934: Северо-Кавказский ФО | G934: Республика Дагестан | J934: понедельник-суббота: 9:00-18:00, воскресенье: выходной | K934: 8 (989) 889-09-09 | L934: sk-udn@mail.ru | M934: =VLOOKUP(G934,справочник!$B$1:$C$94,2,0) -> МСК
A935: Федеральное медико-биологическое агентство (ФМБА России) | B935: 3643 | C935: Северо-Кавказский федеральный научно-клинический центр | D935: 1022601229342 | E935: Научные учреждения | F935: Северо-Кавказский ФО | G935: Ставропольский край | H935: Ессентуки | I935: 357600, Ессентуки, Советская, 24 | J935: Понедельник - пятница: 8:00-17.00, перерыв: 12:00-13:00. | K935: 8(87934) 992-91 | L935: nauka@skfmba.ru | M935: =VLOOKUP(G935,справочник!$B$1:$C$94,2,0) -> МСК
A936: Министерство науки и высшего образования Российской Федерации (Минобрнауки России) | B936: 2344 | C936: Северо-Кавказский федеральный научный аграрный центр | D936: 1022603028194 | E936: Научные учреждения | F936: Северо-Кавказский ФО | G936: Ставропольский край | H936: Михайловск | I936: 356241, Михайловск, Ул Никонова, Д 49 | J936: понедельник- пятница:9:00-16:30 суббота и воскресенье: выходной | K936: 8-(86553)- 2-32-97 | L936: info@fnac.center | M936: =VLOOKUP(G936,справочник!$B$1:$C$94,2,0) -> МСК
A937: Министерство науки и высшего образования Российской Федерации (Минобрнауки России) | B937: 2156 | C937: Северо-Кавказский федеральный научный центр садоводства, виноградарства, виноделия | D937: 1022301810706 | E937: Научные учреждения | F937: Южный ФО | G937: Краснодарский край | H937: Краснодар | I937: 350901, Краснодар, им. 40-летия Победы, 39 | J937: понедельник-четверг: 10:00-17:00 пятница: 10:00-14:00 суббота и воскресенье: выходной | K937: 8(861)252-58-76 | L937: kubansad@kubannet.ru | M937: =VLOOKUP(G937,справочник!$B$1:$C$94,2,0) -> МСК
A938: Министерство науки и высшего образования Российской Федерации (Минобрнауки России) | B938: 194 | C938: Северо-Кавказский федеральный университет | D938: 1022601961580 | E938: Высшее образование | F938: Северо-Кавказский ФО | G938: Ставропольский край | H938: Ставрополь | I938: 355017, Ставрополь, Пушкина, 1 | J938: 09.00-18.00 ежедневно | K938: 8-8652-95-68-13 | L938: selcom@ncfu.ru | M938: =VLOOKUP(G938,справочник!$B$1:$C$94,2,0) -> МСК
A939: Министерство здравоохранения Российской Федерации (Минздрав России) | B939: 652 | C939: Северо-Осетинская государственная медицинская академия» Министерства здравоохранения Российской Федерации | D939: 1021500581024 | E939: Высшее образование | F939: Северо-Кавказский ФО | G939: Республика Северная Осетия - Алания | H939: Владикавказ | I939: 362019, Владикавказ, Пушкинская, 40 | J939: понедельник-пятница: 9:00-17:00, суббота: 9:00-13:00, воскресенье: выходной | K939: +7 (8672) 56-32-81 | L939: sogma.priem@yandex.ru | M939: =VLOOKUP(G939,справочник!$B$1:$C$94,2,0) -> МСК
A940: Министерство науки и высшего образования Российской Федерации (Минобрнауки России) | B940: 360 | C940: Северо-Осетинский государственный университет имени Коста Левановича Хетагурова | D940: 1021500579704 | E940: Высшее образование | F940: Северо-Кавказский ФО | G940: Республика Северная Осетия - Алания | H940: Владикавказ | I940: 362025, Владикавказ, Ватутина, 44-46 | J940: понедельник-суббота: 09:00-17:00 воскресенье: выходной | K940: 8-(8672) 33 39 20 | L940: priem@nosu.ru | M940: =VLOOKUP(G940,справочник!$B$1:$C$94,2,0) -> МСК
A941: Министерство науки и высшего образования Российской Федерации (Минобрнауки России) | B941: 195 | C941: Сибирский государственный автомобильно-дорожный университет (СибАДИ) | D941: 1025500523950 | E941: Высшее образование | F941: Сибирский ФО | G941: Омская область | H941: Омск | I941: 644080, Омск, Проспект Мира, 5 | J941: понедельник - пятница : 9:00-16:00, суббота: 10:00-13:00 воскресенье: выходной | K941: +7-913-601-17-95 | L941: priem_kom@sibadi.org | M941: =VLOOKUP(G941,справочник!$B$1:$C$94,2,0) -> МСК+3
A942: Министерство науки и высшего образования Российской Федерации (Минобрнауки России) | B942: 198 | C942: Сибирский государственный индустриальный университет | D942: 1024201470908 | E942: Высшее образование | F942: Сибирский ФО | G942: Кемеровская область | H942: Новокузнецк | I942: 654007, Новокузнецк, Кирова, 42 | J942: понедельник-четверг: 9:00 – 17:00, пятница: 9:00 – 14:00 | K942: +7(3843) 32-89-49 | L942: pr_com@sibsiu.ru | M942: =VLOOKUP(G942,справочник!$B$1:$C$94,2,0) -> МСК+4
A943: Министерство культуры Российской Федерации (Минкультуры России) | B943: 733 | C943: Сибирский государственный институт искусств имени Дмитрия Хворостовского | D943: 1022402665559 | E943: Высшее образование | F943: Сибирский ФО | G943: Красноярский край | H943: Красноярск | I943: 660049, Красноярск, Ленина, 22 | J943: понедельник-пятница 9:00-17:00 суббота и воскресенье: выходной | K943: +7 (391) 234-54-01 | L943: priem@sibgii.ru | M943: =VLOOKUP(G943,справочник!$B$1:$C$94,2,0) -> МСК+4
A944: Министерство здравоохранения Российской Федерации (Минздрав России) | B944: 705 | C944: Сибирский государственный медицинский университет | D944: 1027000885251 | E944: Высшее образование | F944: Сибирский ФО | G944: Томская область | H944: Томск | I944: 634050, Томск, Московский тракт, 2 | J944: Понедельник-пятница 09:00-17:00; суббота 09:00-12:00; воскресенье выходной. Без обеда/перерыва. | K944: 88002509345 | L944: sannikova.ey@ssmu.ru | M944: =VLOOKUP(G944,справочник!$B$1:$C$94,2,0) -> МСК+4
A945: Федеральное агентство морского и речного транспорта (Росморречфлот) | B945: 953 | C945: Сибирский государственный университет водного транспорта | D945: 1025403202440 | E945: Высшее образование | F945: Сибирский ФО | G945: Новосибирская область | H945: Новосибирск | I945: 630099, Новосибирск, Щетинкина, 33 | J945: Понедельник-четверг: 9:00-18:00 пятница: 9:00-17:30 суббота и воскресенье: выходной | K945: +7 (800) 200-48-63 | L945: v.v.solodskaya@nsawt.ru | M945: =VLOOKUP(G945,справочник!$B$1:$C$94,2,0) -> МСК+4
A946: Министерство науки и высшего образования Российской Федерации (Минобрнауки России) | B946: 196 | C946: Сибирский государственный университет геосистем и технологий | D946: 1025401493061 | E946: Высшее образование | F946: Сибирский ФО | G946: Новосибирская область | H946: Новосибирск | I946: 630108, Новосибирск, Плахотного, 10 | J946: понедельник-: 5:00-13:00 (МСК) пятница: 5:00-11:30(МСК) суббота: 5:00-9:00(МСК) воскресенье: выходной | K946: `+7 (383) 354-98-38 | L946: priem.com@ssga.ru | M946: =VLOOKUP(G946,справочник!$B$1:$C$94,2,0) -> МСК+4
... A1161: Министерство спорта Российской Федерации (Минспорт России) | B1161: 541 | C1161: Чайковская государственная академия физической культуры и спорта | D1161: 1025902030868 | E1161: Высшее образование | F1161: Приволжский ФО | G1161: Пермский край | H1161: Чайковский | I1161: 617764, Чайковский, Ленина, 67 | J1161: 8-34-241-4-74-57 | K1161: 8-34-241-4-74-57 | L1161: 4cekretpk@chgafkis.ru | M1161: =VLOOKUP(G1161,справочник!$B$1:$C$94,2,0) -> МСК+2
A1162: Негосударственная или частная организация | B1162: 7464 | C1162: Частное образовательное учреждение высшего образования Гуманитарный университет им. М.А. Шавхалова | D1162: 1180608000044 | E1162: Высшее образование | F1162: Северо-Кавказский ФО | G1162: Республика Ингушетия | J1162: Понедельник – пятница с 9:00 до 18:00 (перерыв с 13:00 до 14:00); Суббота с 9:00 до 13:00; Воскресенье выходной | K1162: +79286971515 | L1162: gum_univer@mail.ru | M1162: =VLOOKUP(G1162,справочник!$B$1:$C$94,2,0) -> МСК
A1163: Министерство культуры Российской Федерации (Минкультуры России) | B1163: 756 | C1163: Челябинский государственный институт культуры | D1163: 1027402891383 | E1163: Высшее образование | F1163: Уральский ФО | G1163: Челябинская область | H1163: Челябинск | I1163: 454091, Челябинск, Орджоникидзе, 36А | J1163: Понедельник-четверг: 9:00 - 17:00 пятница: 9:00-16:00 суббота: 9:00-14:00 воскресенье: выходной | K1163: +7(351)263-89-41 | L1163: pri-kom@chgaki.ru | M1163: =VLOOKUP(G1163,справочник!$B$1:$C$94,2,0) -> МСК+2
A1164: Министерство науки и высшего образования Российской Федерации (Минобрнауки России) | B1164: 238 | C1164: Челябинский государственный университет | D1164: 1027402324905 | E1164: Высшее образование | F1164: Уральский ФО | G1164: Челябинская область | H1164: Челябинск | I1164: 454001, Челябинск, Братьев Кашириных, 129 | J1164: График работы прямого номера телефона До 20.06.2026 понедельник-четверг: с 8:00 до 17:00 пятница: с 8:00 до 15:45 суббота, воскресенье выходной с 20.06.2026 понедельник - пятница: с 8:00 до 17:00 суббота: с 8:00 до 14:00 воскресенье выходной | K1164: 8 (351) 799-70-01 | L1164: abit@csu.ru | M1164: =VLOOKUP(G1164,справочник!$B$1:$C$94,2,0) -> МСК+2
A1165: Министерство науки и высшего образования Российской Федерации (Минобрнауки России) | B1165: 239 | C1165: Череповецкий государственный университет | D1165: 1023501255348 | E1165: Высшее образование | F1165: Северо-Западный ФО | G1165: Вологодская область | H1165: Череповец | I1165: 162600, Череповец, проспект Луначарского, 5 | J1165: понедельник-четверг: 9:00-17:30 пятница: 9:00-15:00 суббота и воскресенье: выходной | K1165: +7 (8202) 51-71-88, 51-81-70 | L1165: priemka@chsu.ru | M1165: =VLOOKUP(G1165,справочник!$B$1:$C$94,2,0) -> МСК
A1166: Министерство обороны Российской Федерации (Минобороны России) | B1166: 3775 | C1166: Черноморское высшее военноморское училище имени П.С. Нахимова | D1166: 1149204009580 | E1166: Высшее образование | F1166: Южный ФО | G1166: г.Севастополь | H1166: Севастополь | I1166: 299028, Севастополь, улица Павла Дыбенко, 1а | J1166: понедельник-пятница: 9:00-16:00 суббота и воскресенье: выходной | K1166: +79788366050 | L1166: f_sies@sev-chvvmu.ru | M1166: =VLOOKUP(G1166,справочник!$B$1:$C$94,2,0) -> МСК
A1167: Министерство просвещения Российской Федерации (Минпросвещения России) | B1167: 240 | C1167: Чеченский государственный педагогический университет | D1167: 1022002546323 | E1167: Высшее образование | F1167: Северо-Кавказский ФО | G1167: Чеченская Республика | H1167: Грозный | I1167: 364037, Грозный, Субры Кишиевой, 33 | J1167: Понедельник-суббота с 9:00-18:00, выходной: воскресенье | K1167: +7 (928) 475-82-54 | L1167: rumisaelmurzaeva@mail.ru | M1167: =VLOOKUP(G1167,справочник!$B$1:$C$94,2,0) -> МСК
A1168: Министерство науки и высшего образования Российской Федерации (Минобрнауки России) | B1168: 241 | C1168: Чеченский государственный университет имени Ахмата Абдулхамидовича Кадырова | D1168: 1032001202903 | E1168: Высшее образование | F1168: Северо-Кавказский ФО | G1168: Чеченская Республика | H1168: Грозный | I1168: 364024, Грозный, ул. А. Шерипова, 32 | J1168: понедельник-пятница: 9-00 до 18-00 суббота: 9-00 до 14-00 перерыв: 12-00до 13-00 | K1168: +7 (8712) 29-55-53 | L1168: pk@chesu.ru | M1168: =VLOOKUP(G1168,справочник!$B$1:$C$94,2,0) -> МСК
A1169: Министерство здравоохранения Российской Федерации (Минздрав России) | B1169: 554 | C1169: Читинская государственная медицинская академия Министерства здравоохранения Российской Федерации | D1169: 1027501147960 | E1169: Высшее образование | F1169: Дальневосточный ФО | G1169: Забайкальский край | H1169: Чита | I1169: 672000, Чита, Горького, 39 | J1169: понедельник-пятница: 10:00-17:00, суббота и воскресенье: выходной | K1169: 8(3022)217438 | L1169: priem@chitgma.ru | M1169: =VLOOKUP(G1169,справочник!$B$1:$C$94,2,0) -> МСК+6
A1170: Министерство сельского хозяйства Российской Федерации (Минсельхоз России) | B1170: 1499 | C1170: Чувашский государственный аграрный университет | D1170: 1022101131150 | E1170: Высшее образование | F1170: Приволжский ФО | G1170: Чувашская Республика | H1170: Чебоксары | I1170: 428003, Чебоксары, К. Маркса, 29 | J1170: понедельник - пятница: 8:00-17:00, суббота и воскресенье: выходной | K1170: 8(8352) 62-21-55 | L1170: pk@academy21.ru | M1170: =VLOOKUP(G1170,справочник!$B$1:$C$94,2,0) -> МСК
A1171: Субъект Российской Федерации | B1171: 3167 | C1171: Чувашский государственный институт культуры и искусств Министерства культуры, по делам национальностей и архивного дела Чувашской Республики | D1171: 1022101268970 | E1171: Высшее образование | F1171: Приволжский ФО | G1171: Чувашская Республика | H1171: Чебоксары | I1171: 428023, Чебоксары, Энтузиастов, 26 | J1171: ПН-ПТ 9.00-17.00 ОБЕД 12.00-13.00 СУББ 9.00-14.00 ОБЕД 12.00-13.00 | K1171: 8(8352) 33-05-15; 8(8352) 33-09-69 | L1171: chgiki-priem@mail.ru | M1171: =VLOOKUP(G1171,справочник!$B$1:$C$94,2,0) -> МСК
A1172: Министерство просвещения Российской Федерации (Минпросвещения России) | B1172: 243 | C1172: Чувашский государственный педагогический университет им. И.Я. Яковлева | D1172: 1022101133218 | E1172: Высшее образование | F1172: Приволжский ФО | G1172: Чувашская Республика | H1172: Чебоксары | I1172: 428000, Чебоксары, Карла Маркса, 38 | J1172: понедельник-пятница: 9:00-18:00 суббота: 9:00-14:00 воскресенье: выходной | K1172: 8(8352)22-04-80 | L1172: priem@chuvgpu.ru | M1172: =VLOOKUP(G1172,справочник!$B$1:$C$94,2,0) -> МСК
A1173: Министерство науки и высшего образования Российской Федерации (Минобрнауки России) | B1173: 244 | C1173: Чувашский государственный университет имени И.Н. Ульянова | D1173: 1022101274315 | E1173: Высшее образование | F1173: Приволжский ФО | G1173: Чувашская Республика | H1173: Чебоксары | I1173: 428015, Чебоксары, Московский проспект, 15 | J1173: понедельник-пятница: 9:00-18:00 суббота: 9:00-14:00 воскресенье: выходной | K1173: 8-(8352)-45-23-39 | L1173: priemkomchgu@rambler.ru | M1173: =VLOOKUP(G1173,справочник!$B$1:$C$94,2,0) -> МСК
A1174: Министерство спорта Российской Федерации (Минспорт России) | B1174: 552 | C1174: Чурапчинский государственный институт физической культуры и спорта | D1174: 1021400920090 | E1174: Высшее образование | F1174: Дальневосточный ФО | G1174: Республика Саха (Якутия) | H1174: Чурапча | I1174: 678671, Чурапча, Спортивная, 2 | J1174: понедельник - пятница; 09.00-18.00 (обеденный перерыв 13.00-14.00); суббота, воскресенье - выходные дни | K1174: 8 (914) 300-85-55; 8 (41151)-43-200 | L1174: pk@chgifkis.ru; rector@chgifkis.ru | M1174: =VLOOKUP(G1174,справочник!$B$1:$C$94,2,0) -> МСК+6
... A1199: Министерство науки и высшего образования Российской Федерации (Минобрнауки России) | B1199: 251 | C1199: Ярославский государственный университет им. П.Г. Демидова | D1199: 1027600680249 | E1199: Высшее образование | F1199: Центральный ФО | G1199: Ярославская область | H1199: Ярославль | I1199: 150003, Ярославль, ул. Советская, 14 | J1199: Понедельник – пятница: 9:00 - 16:00 Суббота: 10:00 - 13:00 Воскресенье: выходной | K1199: 8 (4852) 30-32-10 | L1199: priem@uniyar.ac.ru | M1199: =VLOOKUP(G1199,справочник!$B$1:$C$94,2,0) -> МСК

Sheet справочник
A1: Абакан | B1: Республика Хакасия | C1: МСК+4
A2: Анадырь | B2: Чукотский автономный округ | C2: МСК+9
A3: Архангельск | B3: Архангельская область | C3: МСК
A4: Астрахань | B4: Астраханская область | C4: МСК+1
A5: Барнаул | B5: Алтайский край | C5: МСК+4
A6: Белгород | B6: Белгородская область | C6: МСК
A7: Биробиджан | B7: Еврейская автономная область | C7: МСК+7
A8: Благовещенск | B8: Амурская область | C8: МСК+6
A9: Брянск | B9: Брянская область | C9: МСК
A10: Великий Новгород | B10: Новгородская область | C10: МСК
A11: Владивосток | B11: Приморский край | C11: МСК+7
A12: Владикавказ | B12: Республика Северная Осетия - Алания | C12: МСК
... A94: Херсон | B94: Херсонская область | C94: МСК

Sheet примеч
A1: Абакан | B1: Республика Хакасия | C1: UTC+7
A2: Анадырь | B2: Чукотский автономный округ | C2: UTC+12
A3: Архангельск | B3: Архангельская область | C3: UTC+3
A4: Астрахань | B4: Астраханская область | C4: UTC+4
A5: Барнаул | B5: Алтайский край | C5: UTC+7
A6: Белгород | B6: Белгородская область | C6: UTC+3
A7: Биробиджан | B7: Еврейская автономная область | C7: UTC+10
A8: Благовещенск | B8: Амурская область | C8: UTC+9
A9: Брянск | B9: Брянская область | C9: UTC+3
A10: Великий Новгород | B10: Новгородская область | C10: UTC+3
A11: Владивосток | B11: Приморский край | C11: UTC+10
A12: Владикавказ | B12: Республика Северная Осетия - Алания | C12: UTC+3
... A83: Ярославль | B83: Ярославская область | C83: UTC+3
